dev_utilities/__about__.py
dev_utilities/__init__.py
dev_utilities/dev_conversors/__init__.py
dev_utilities/dev_conversors/main.py
dev_utilities/git_policy_jira/__init__.py
dev_utilities/git_policy_jira/check_branch_name.py
dev_utilities/git_policy_jira/check_commits_are_signed.py
dev_utilities/git_policy_jira/create_branch_from_jira_issue.py
dev_utilities/git_policy_jira/create_non_jira_branch.py
dev_utilities/git_policy_jira/prepare_commit_msg_from_jira_issue.py
dev_utilities-0.0.2.dist-info/METADATA
dev_utilities-0.0.2.dist-info/WHEEL
dev_utilities-0.0.2.dist-info/entry_points.txt
dev_utilities-0.0.2.dist-info/licenses/LICENSE.txt
dev_utilities-0.0.2.dist-info/RECORD
