Metadata-Version: 2.2
Name: dev-utilities
Version: 0.0.2
Project-URL: Source, https://github.com/jdev-ops/dev-utilities
Author-email: José Albert Cruz Almaguer <jalbertcruz@gmail.com>
License-Expression: MIT
License-File: LICENSE.txt
Classifier: Programming Language :: Python :: 3.10
Classifier: Programming Language :: Python :: 3.11
Classifier: Programming Language :: Python :: 3.12
Classifier: Programming Language :: Python :: Implementation :: CPython
Requires-Python: >=3.10
Requires-Dist: cattrs~=23.2.3
Requires-Dist: gitpython~=3.1.41
Requires-Dist: jinja2~=3.1.3
Requires-Dist: pydot~=2.0.0
Requires-Dist: python-decouple~=3.8
Requires-Dist: python-slugify~=8.0.1
Requires-Dist: requests~=2.31.0
Requires-Dist: typer~=0.9.0
